detection/__init__.py
detection/face_detection.py
detection/full_detection.py
detection/voice_detection.py
fvmouse-1.0.6.data/data/detection/data/optimized_model.eim
fvmouse-1.0.6.data/data/detection/data/shape_predictor_68_face_landmarks.dat
fvmouse-1.0.6.dist-info/METADATA
fvmouse-1.0.6.dist-info/WHEEL
fvmouse-1.0.6.dist-info/entry_points.txt
fvmouse-1.0.6.dist-info/top_level.txt
fvmouse-1.0.6.dist-info/RECORD
