Metadata-Version: 2.1
Name: fvmouse
Version: 1.0.6
Summary: Face and voice recognition system to control the cursor
Home-page: UNKNOWN
License: Proprietary
Platform: UNKNOWN
Classifier: License :: Other/Proprietary License
Classifier: Programming Language :: Python :: 3.10
Requires-Dist: dlib (~=19.24.0)
Requires-Dist: edge-impulse-linux (~=1.0.7)
Requires-Dist: numpy (~=1.23.2)
Requires-Dist: opencv-python (~=4.5.5.64)
Requires-Dist: PyAutoGUI (~=0.9.53)
Requires-Dist: pynput (~=1.7.6)
Requires-Dist: PySimpleGUI (~=4.60.4)
Requires-Dist: pyaudio (~=0.2.13)
